cppjieba_pybind.cpython-37m-darwin.so
cppjieba/CppJieba.py
cppjieba/__init__.py
cppjieba/dict/README.md
cppjieba/dict/hmm_model.utf8
cppjieba/dict/idf.utf8
cppjieba/dict/jieba.dict.utf8
cppjieba/dict/stop_words.utf8
cppjieba/dict/user.dict.utf8
cppjieba/dict/pos_dict/char_state_tab.utf8
cppjieba/dict/pos_dict/prob_emit.utf8
cppjieba/dict/pos_dict/prob_start.utf8
cppjieba/dict/pos_dict/prob_trans.utf8
cppjieba/pybind/cppjieba_pybind.cc
cppjieba-0.1.1.data/data/cppjieba/deps/limonp/ArgvContext.hpp
cppjieba-0.1.1.data/data/cppjieba/deps/limonp/BlockingQueue.hpp
cppjieba-0.1.1.data/data/cppjieba/deps/limonp/BoundedBlockingQueue.hpp
cppjieba-0.1.1.data/data/cppjieba/deps/limonp/BoundedQueue.hpp
cppjieba-0.1.1.data/data/cppjieba/deps/limonp/Closure.hpp
cppjieba-0.1.1.data/data/cppjieba/deps/limonp/Colors.hpp
cppjieba-0.1.1.data/data/cppjieba/deps/limonp/Condition.hpp
cppjieba-0.1.1.data/data/cppjieba/deps/limonp/Config.hpp
cppjieba-0.1.1.data/data/cppjieba/deps/limonp/FileLock.hpp
cppjieba-0.1.1.data/data/cppjieba/deps/limonp/ForcePublic.hpp
cppjieba-0.1.1.data/data/cppjieba/deps/limonp/LocalVector.hpp
cppjieba-0.1.1.data/data/cppjieba/deps/limonp/Logging.hpp
cppjieba-0.1.1.data/data/cppjieba/deps/limonp/Md5.hpp
cppjieba-0.1.1.data/data/cppjieba/deps/limonp/MutexLock.hpp
cppjieba-0.1.1.data/data/cppjieba/deps/limonp/NonCopyable.hpp
cppjieba-0.1.1.data/data/cppjieba/deps/limonp/StdExtension.hpp
cppjieba-0.1.1.data/data/cppjieba/deps/limonp/StringUtil.hpp
cppjieba-0.1.1.data/data/cppjieba/deps/limonp/Thread.hpp
cppjieba-0.1.1.data/data/cppjieba/deps/limonp/ThreadPool.hpp
cppjieba-0.1.1.data/data/cppjieba/include/cppjieba/DictTrie.hpp
cppjieba-0.1.1.data/data/cppjieba/include/cppjieba/FullSegment.hpp
cppjieba-0.1.1.data/data/cppjieba/include/cppjieba/HMMModel.hpp
cppjieba-0.1.1.data/data/cppjieba/include/cppjieba/HMMSegment.hpp
cppjieba-0.1.1.data/data/cppjieba/include/cppjieba/Jieba.hpp
cppjieba-0.1.1.data/data/cppjieba/include/cppjieba/KeywordExtractor.hpp
cppjieba-0.1.1.dist-info/METADATA
cppjieba-0.1.1.dist-info/WHEEL
cppjieba-0.1.1.dist-info/top_level.txt
cppjieba-0.1.1.dist-info/RECORD
